[
    {
      "Courseid": "IS117"
    },
    {
      "Courseid": "IS218"
    },
    {
      "Courseid": "IS219"
    },
    {
      "Courseid": "IS247"
    },
    {
      "Courseid": "IS265"
    },
    {
      "Courseid": "IS322"
    },
    {
      "Courseid": "IS331"
    },
    {
      "Courseid": "IS344"
    },
    {
      "Courseid": "IS350"
    },
    {
      "Courseid": "IS375"
    },
    {
      "Courseid": "IS390"
    },
    {
      "Courseid": "IS392"
    },
    {
      "Courseid": "IS421"
    },
    {
      "Courseid": "IS448"
    },
    {
      "Courseid": "IS455"
    },
    {
      "Courseid": "IS465"
    },
    {
      "Courseid": "IS488"
    },
    {
      "Courseid": "IS489"
    },
    {
      "Courseid": "IS491"
    },
    {
      "Courseid": "IS591"
    },
    {
      "Courseid": "IS601"
    },
    


    {
      "Courseid": "CS100"
    },
    {
      "Courseid": "CS101"
    },
    {
      "Courseid": "CS103"
    },
    {
      "Courseid": "CS104"
    },
    {
      "Courseid": "CS113"
    },
    {
      "Courseid": "CS114"
    },
    {
      "Courseid": "CS115"
    },
    {
      "Courseid": "CS116"
    },
    {
      "Courseid": "CS210"
    },
    {
      "Courseid": "CS241"
    },
    {
      "Courseid": "CS280"
    },
    {
      "Courseid": "CS288"
    },
    {
      "Courseid": "CS301"
    },
    {
      "Courseid": "CS331"
    },
    {
      "Courseid": "CS332"
    },
    {
      "Courseid": "CS337"
    },
    {
      "Courseid": "CS341"
    },
    {
      "Courseid": "CS350"
    },
    {
      "Courseid": "CS351"
    },
    {
      "Courseid": "CS356"
    }
]